termynal/__init__.py
termynal/markdown.py
termynal/plugin.py
termynal/assets/termynal.css
termynal/assets/termynal.js
termynal-0.13.1.dist-info/METADATA
termynal-0.13.1.dist-info/WHEEL
termynal-0.13.1.dist-info/entry_points.txt
termynal-0.13.1.dist-info/licenses/LICENSE
termynal-0.13.1.dist-info/RECORD
