Metadata-Version: 2.4
Name: termynal
Version: 0.13.1
Summary: A lightweight and modern animated terminal window
Project-URL: Homepage, https://termynal.github.io/termynal.py/
Project-URL: Changelog, https://termynal.github.io/termynal.py/changelog/
Project-URL: Repository, https://github.com/termynal/termynal.py
Project-URL: Documentation, https://termynal.github.io/termynal.py/
Author: Danil Akhtarov
Author-email: daxartio@gmail.com
License: MIT License
License-File: LICENSE
Keywords: markdown,mkdocs,plugin,termynal
Requires-Python: >=3.9
Requires-Dist: markdown>=3
Provides-Extra: mkdocs
Requires-Dist: mkdocs>=1.4; extra == 'mkdocs'
